{
    "header": {
        "avatar": "/static/images/profile-timyeo.jpg",
        "name": "The Quiet Achiever",
        "content": "Author | Coach | Podcast<br><br>Tiny habits to have impact at work (without pretending to be an extrovert).<br><br>Follow me 👇🏻"
    },
    "links": [
        {
            "id": "6d4534e0",
            "title": "Follow on Linkedin",
            "href": "https://www.thequietachievr.com/followonlinkedin",
            "image": "/static/images/icon-linkedin.svg"
        },
        {
            "id": "6d4534e0",
            "title": "Buy the book",
            "href": "https://mybook.to/thequietachiever/opt/1?iguid=VOkXVuwjvEeN-O3PzV88QQ",
            "image": "/static/images/icon-book.jpg"
        },
        {
            "id": "728c7815",
            "title": "Courses @ The Quiet Achiever School",
            "href": "https://www.thequietachievr.com/school",
            "image": ""
        },
        {
            "id": "39597e4e",
            "title": "Coaching - Book a Chemistry Call",
            "href": "https://www.thequietachievr.com/chemistrycall",
            "image": ""
        },
        {
            "id": "d323b0e5",
            "title": "Podcast - Listen Now",
            "href": "https://www.thequietachievr.com/podcast",
            "image": ""
        },
        {
            "id": "9c6fa6f5",
            "title": "Signup for Newsletter",
            "href": "https://www.thequietachievr.com/book#newsletter",
            "image": ""
        }
    ],
    "socials": [
        {
            "title": "Linkedin",
            "href": "https://www.thequietachievr.com/followonlinkedin",
            "component": "linkedin"
        },
        {
            "title": "YouTube",
            "href": "https://www.youtube.com/@thequietachievr",
            "component": "youtube"
        },
        {
            "title": "Instagram",
            "href": "https://www.instagram.com/thequietachievr",
            "component": "instagram"
        },
        {
            "title": "Facebook",
            "href": "https://www.facebook.com/thequietachievr",
            "component": "facebook"
        },
        {
            "title": "Threads",
            "href": "https://www.threads.net/@thequietachievr",
            "component": "threads"
        },
        {
            "title": "TikTok",
            "href": "https://www.tiktok.com/@thequietachievr",
            "component": "tiktok"
        }
        
    ]
}